setup.py
src/prettylogger/__init__.py
src/prettylogger/tests.py
src/prettylogger/utils.py
src/prettylogger.egg-info/PKG-INFO
src/prettylogger.egg-info/SOURCES.txt
src/prettylogger.egg-info/dependency_links.txt
src/prettylogger.egg-info/requires.txt
src/prettylogger.egg-info/top_level.txt