Metadata-Version: 1.0
Name: prettylogger
Version: 0.1.0
Summary: Logs things in color and beautiful format.
Home-page: http://github.com/arnellebalane/prettylogger
Author: Arnelle Balane
Author-email: arnellebalane@gmail.com
License: MIT
Platform: UNKNOWN
